odoo8_addon_purchase_order_line_description-8.0.1.0.0-py2.7-nspkg.pth
odoo_addons/purchase_order_line_description/__openerp__.py
odoo_addons/purchase_order_line_description/__init__.py
odoo_addons/purchase_order_line_description/README.rst
odoo_addons/purchase_order_line_description/security/res_groups_security.xml
odoo_addons/purchase_order_line_description/models/__init__.py
odoo_addons/purchase_order_line_description/models/purchase_config_settings.py
odoo_addons/purchase_order_line_description/models/purchase_order_line.py
odoo_addons/purchase_order_line_description/i18n/it.po
odoo_addons/purchase_order_line_description/views/purchase_config_settings_view.xml
odoo_addons/purchase_order_line_description/tests/test_purchase_order_line_description.py
odoo_addons/purchase_order_line_description/tests/__init__.py
odoo_addons/purchase_order_line_description/static/description/icon.png
odoo8_addon_purchase_order_line_description-8.0.1.0.0.dist-info/top_level.txt
odoo8_addon_purchase_order_line_description-8.0.1.0.0.dist-info/WHEEL
odoo8_addon_purchase_order_line_description-8.0.1.0.0.dist-info/RECORD
odoo8_addon_purchase_order_line_description-8.0.1.0.0.dist-info/metadata.json
odoo8_addon_purchase_order_line_description-8.0.1.0.0.dist-info/DESCRIPTION.rst
odoo8_addon_purchase_order_line_description-8.0.1.0.0.dist-info/METADATA
odoo8_addon_purchase_order_line_description-8.0.1.0.0.dist-info/namespace_packages.txt
